ggrab/__init__.py
ggrab/ggrab.py
ggrab-0.1.0a15.dist-info/METADATA
ggrab-0.1.0a15.dist-info/WHEEL
ggrab-0.1.0a15.dist-info/entry_points.txt
ggrab-0.1.0a15.dist-info/top_level.txt
ggrab-0.1.0a15.dist-info/RECORD
