Metadata-Version: 2.1
Name: ggrab
Version: 0.1.0a15
Summary: A CLI tool for extracting and sharing code files and functions. A manual context builder for pasting into llms.
Author-email: Keizo Gates <keizo@grugnotes.com>
License: MIT
Project-URL: Homepage, https://github.com/keizo/ggrab
Project-URL: Issues, https://github.com/keizo/ggrab/issues
Classifier: Development Status :: 3 - Alpha
Classifier: Environment :: Console
Classifier: Intended Audience :: Developers
Classifier: License :: OSI Approved :: MIT License
Classifier: Operating System :: OS Independent
Classifier: Programming Language :: Python :: 3
Classifier: Programming Language :: Python :: 3.7
Classifier: Programming Language :: Python :: 3.8
Classifier: Programming Language :: Python :: 3.9
Classifier: Programming Language :: Python :: 3.10
Classifier: Programming Language :: Python :: 3.11
Classifier: Topic :: Software Development :: Libraries :: Python Modules
Requires-Python: >=3.7
Requires-Dist: argcomplete
Requires-Dist: pyperclip
Requires-Dist: tiktoken
Requires-Dist: esprima
